fitgrid/__init__.py
fitgrid/defaults.py
fitgrid/epochs.py
fitgrid/errors.py
fitgrid/fake_data.py
fitgrid/fitgrid.py
fitgrid/io.py
fitgrid/models.py
fitgrid/plots.py
fitgrid/tools.py
fitgrid/utils/__init__.py
fitgrid/utils/lm.py
fitgrid/utils/lmer.py
fitgrid/utils/summary.py
fitgrid-0.4.3.dist-info/LICENSE
fitgrid-0.4.3.dist-info/METADATA
fitgrid-0.4.3.dist-info/WHEEL
fitgrid-0.4.3.dist-info/top_level.txt
fitgrid-0.4.3.dist-info/RECORD
