Metadata-Version: 2.1
Name: fitgrid
Version: 0.4.3
Summary: Mass multiple regression manager
Home-page: https://github.com/kutaslab/fitgrid
Author: Thomas P. Urbach, Andrey Portnoy
Author-email: turbach@ucsd.edu, aportnoy@ucsd.edu
License: BSD-3-Clause
Platform: UNKNOWN
Requires-Dist: patsy
Requires-Dist: statsmodels
Requires-Dist: matplotlib
Requires-Dist: scipy
Requires-Dist: tqdm
Requires-Dist: tables
